raw_pillow_opener/__init__.py
raw_pillow_opener-0.1.0.dist-info/LICENSE
raw_pillow_opener-0.1.0.dist-info/METADATA
raw_pillow_opener-0.1.0.dist-info/WHEEL
raw_pillow_opener-0.1.0.dist-info/top_level.txt
raw_pillow_opener-0.1.0.dist-info/RECORD
