Metadata-Version: 2.1
Name: raw-pillow-opener
Version: 0.1.0
Summary: raw-pillow-opener is a simple raw image opener for Pillow base on rawpy.
Home-page: https://github.com/samuelduann/raw-pillow-opener
Author: Samuel Duann
Author-email: adamgic@gmail.com
License: MIT
Download-URL: https://github.com/samuelduann/raw-pillow-opener/archive/v0.1.0.tar.gz
Keywords: nef,raw,Pillow
Platform: UNKNOWN
Classifier: Intended Audience :: Developers
Classifier: License :: OSI Approved :: MIT License
Classifier: Natural Language :: English
Classifier: Operating System :: MacOS :: MacOS X
Classifier: Operating System :: POSIX :: Linux
Classifier: Programming Language :: Python :: 3
Classifier: Programming Language :: Python :: 3.6
Classifier: Programming Language :: Python :: 3.7
Classifier: Programming Language :: Python :: 3.8
Classifier: Programming Language :: Python :: Implementation :: PyPy
Classifier: Topic :: Multimedia :: Graphics
Requires-Dist: rawpy (==0.16.0)
